{
"meta":{"test_sets":[],"test_metrics":[],"learn_metrics":[{"best_value":"Min","name":"RMSE"}],"launch_mode":"Train","parameters":"","iteration_count":100,"learn_sets":["learn"],"name":"experiment"},
"iterations":[
{"learn":[14.005006],"iteration":0,"passed_time":0.0007034521739,"remaining_time":0.06964176521},
{"learn":[13.14441192],"iteration":1,"passed_time":0.001421739462,"remaining_time":0.06966523364},
{"learn":[12.34258257],"iteration":2,"passed_time":0.00205143269,"remaining_time":0.06632965698},
{"learn":[11.64527793],"iteration":3,"passed_time":0.002570027774,"remaining_time":0.06168066658},
{"learn":[11.02766183],"iteration":4,"passed_time":0.003191107442,"remaining_time":0.06063104139},
{"learn":[10.43485794],"iteration":5,"passed_time":0.00393283712,"remaining_time":0.06161444821},
{"learn":[9.890641275],"iteration":6,"passed_time":0.004728696738,"remaining_time":0.0628241138},
{"learn":[9.492161212],"iteration":7,"passed_time":0.005325383138,"remaining_time":0.06124190609},
{"learn":[9.105082953],"iteration":8,"passed_time":0.005975097755,"remaining_time":0.0604148773},
{"learn":[8.674157135],"iteration":9,"passed_time":0.006572104706,"remaining_time":0.05914894235},
{"learn":[8.341743544],"iteration":10,"passed_time":0.007139290581,"remaining_time":0.05776335106},
{"learn":[8.049372916],"iteration":11,"passed_time":0.007769152614,"remaining_time":0.05697378584},
{"learn":[7.757318612],"iteration":12,"passed_time":0.008297436046,"remaining_time":0.05552899508},
{"learn":[7.522206899],"iteration":13,"passed_time":0.008891171946,"remaining_time":0.05461719909},
{"learn":[7.297756655],"iteration":14,"passed_time":0.009462392088,"remaining_time":0.05362022183},
{"learn":[7.088359431],"iteration":15,"passed_time":0.01001212008,"remaining_time":0.05256363043},
{"learn":[6.882113791],"iteration":16,"passed_time":0.0105582035,"remaining_time":0.05154887589},
{"learn":[6.704728832],"iteration":17,"passed_time":0.01111787753,"remaining_time":0.05064810877},
{"learn":[6.563881962],"iteration":18,"passed_time":0.01167292289,"remaining_time":0.04976351339},
{"learn":[6.418790279],"iteration":19,"passed_time":0.01218203076,"remaining_time":0.04872812304},
{"learn":[6.315756953],"iteration":20,"passed_time":0.01268077506,"remaining_time":0.04770386807},
{"learn":[6.210157751],"iteration":21,"passed_time":0.01318520845,"remaining_time":0.04674755724},
{"learn":[6.115058449],"iteration":22,"passed_time":0.01365828716,"remaining_time":0.04572557005},
{"learn":[6.014819884],"iteration":23,"passed_time":0.01421664577,"remaining_time":0.04501937828},
{"learn":[5.93117229],"iteration":24,"passed_time":0.01506087171,"remaining_time":0.04518261512},
{"learn":[5.844857622],"iteration":25,"passed_time":0.01558521964,"remaining_time":0.04435793282},
{"learn":[5.771145213],"iteration":26,"passed_time":0.01622743499,"remaining_time":0.04387417608},
{"learn":[5.704018229],"iteration":27,"passed_time":0.01682298285,"remaining_time":0.04325909876},
{"learn":[5.665806474],"iteration":28,"passed_time":0.0175167377,"remaining_time":0.04288580609},
{"learn":[5.616500369],"iteration":29,"passed_time":0.01823025085,"remaining_time":0.04253725198},
{"learn":[5.558023666],"iteration":30,"passed_time":0.01912620663,"remaining_time":0.04257123412},
{"learn":[5.510080976],"iteration":31,"passed_time":0.01971315441,"remaining_time":0.04189045311},
{"learn":[5.468747792],"iteration":32,"passed_time":0.0202293934,"remaining_time":0.04107179872},
{"learn":[5.429275534],"iteration":33,"passed_time":0.02074653568,"remaining_time":0.04027268691},
{"learn":[5.402117324],"iteration":34,"passed_time":0.02123002105,"remaining_time":0.03942718195},
{"learn":[5.367635151],"iteration":35,"passed_time":0.02176201281,"remaining_time":0.03868802278},
{"learn":[5.345181232],"iteration":36,"passed_time":0.02225140009,"remaining_time":0.03788751907},
{"learn":[5.319151269],"iteration":37,"passed_time":0.02274674583,"remaining_time":0.03711311162},
{"learn":[5.296134146],"iteration":38,"passed_time":0.02323317542,"remaining_time":0.03633906925},
{"learn":[5.269629003],"iteration":39,"passed_time":0.02375150203,"remaining_time":0.03562725305},
{"learn":[5.251147059],"iteration":40,"passed_time":0.02427875647,"remaining_time":0.03493772273},
{"learn":[5.248003302],"iteration":41,"passed_time":0.02445864188,"remaining_time":0.03377621975},
{"learn":[5.232376509],"iteration":42,"passed_time":0.02492282599,"remaining_time":0.03303723445},
{"learn":[5.213524255],"iteration":43,"passed_time":0.02539907248,"remaining_time":0.03232609225},
{"learn":[5.189691584],"iteration":44,"passed_time":0.02587546714,"remaining_time":0.03162557094},
{"learn":[5.166052198],"iteration":45,"passed_time":0.02639087018,"remaining_time":0.03098058674},
{"learn":[5.140406659],"iteration":46,"passed_time":0.02687800193,"remaining_time":0.03030923622},
{"learn":[5.118929684],"iteration":47,"passed_time":0.02737602073,"remaining_time":0.02965735579},
{"learn":[5.108792602],"iteration":48,"passed_time":0.02785320822,"remaining_time":0.02899007387},
{"learn":[5.098141225],"iteration":49,"passed_time":0.02832258578,"remaining_time":0.02832258578},
{"learn":[5.085926393],"iteration":50,"passed_time":0.02883455975,"remaining_time":0.0277037927},
{"learn":[5.067816804],"iteration":51,"passed_time":0.02939277649,"remaining_time":0.02713179369},
{"learn":[5.049834901],"iteration":52,"passed_time":0.02992980189,"remaining_time":0.02654152243},
{"learn":[5.03838627],"iteration":53,"passed_time":0.03042179846,"remaining_time":0.02591486535},
{"learn":[5.033534248],"iteration":54,"passed_time":0.03075499502,"remaining_time":0.02516317774},
{"learn":[5.023726885],"iteration":55,"passed_time":0.03130191887,"remaining_time":0.02459436483},
{"learn":[5.01290392],"iteration":56,"passed_time":0.03190149382,"remaining_time":0.02406603919},
{"learn":[5.005569127],"iteration":57,"passed_time":0.03253092935,"remaining_time":0.02355687987},
{"learn":[4.989969032],"iteration":58,"passed_time":0.03321803255,"remaining_time":0.02308371753},
{"learn":[4.976762446],"iteration":59,"passed_time":0.03403488508,"remaining_time":0.02268992339},
{"learn":[4.967222715],"iteration":60,"passed_time":0.03459040004,"remaining_time":0.0221151738},
{"learn":[4.954407599],"iteration":61,"passed_time":0.03512712195,"remaining_time":0.02152952635},
{"learn":[4.942125056],"iteration":62,"passed_time":0.03563750573,"remaining_time":0.02092996368},
{"learn":[4.930230716],"iteration":63,"passed_time":0.03612773523,"remaining_time":0.02032185107},
{"learn":[4.921695642],"iteration":64,"passed_time":0.03663592365,"remaining_time":0.01972703581},
{"learn":[4.906405625],"iteration":65,"passed_time":0.03712464019,"remaining_time":0.01912481464},
{"learn":[4.894330248],"iteration":66,"passed_time":0.03773640863,"remaining_time":0.01858658932},
{"learn":[4.88211557],"iteration":67,"passed_time":0.03830833183,"remaining_time":0.01802745027},
{"learn":[4.877946398],"iteration":68,"passed_time":0.03883206201,"remaining_time":0.01744628873},
{"learn":[4.863182126],"iteration":69,"passed_time":0.03934610922,"remaining_time":0.01686261824},
{"learn":[4.84646533],"iteration":70,"passed_time":0.03991849305,"remaining_time":0.0163047366},
{"learn":[4.838014752],"iteration":71,"passed_time":0.04042945867,"remaining_time":0.01572256726},
{"learn":[4.82981137],"iteration":72,"passed_time":0.04095661164,"remaining_time":0.01514833581},
{"learn":[4.817094767],"iteration":73,"passed_time":0.0415447644,"remaining_time":0.01459680911},
{"learn":[4.808314151],"iteration":74,"passed_time":0.04202445345,"remaining_time":0.01400815115},
{"learn":[4.796235023],"iteration":75,"passed_time":0.04250770447,"remaining_time":0.01342348562},
{"learn":[4.784434534],"iteration":76,"passed_time":0.04304707338,"remaining_time":0.01285821672},
{"learn":[4.774402487],"iteration":77,"passed_time":0.04350831955,"remaining_time":0.01227157731},
{"learn":[4.76731896],"iteration":78,"passed_time":0.04398721845,"remaining_time":0.0116928049},
{"learn":[4.75934113],"iteration":79,"passed_time":0.04448604356,"remaining_time":0.01112151089},
{"learn":[4.754106378],"iteration":80,"passed_time":0.04495772602,"remaining_time":0.01054563944},
{"learn":[4.744002932],"iteration":81,"passed_time":0.0454753002,"remaining_time":0.00998238297},
{"learn":[4.731700554],"iteration":82,"passed_time":0.04615428278,"remaining_time":0.009453286835},
{"learn":[4.723284153],"iteration":83,"passed_time":0.0469472763,"remaining_time":0.008942338343},
{"learn":[4.712232782],"iteration":84,"passed_time":0.04754038008,"remaining_time":0.008389478837},
{"learn":[4.703046867],"iteration":85,"passed_time":0.04822210665,"remaining_time":0.007850110385},
{"learn":[4.698601855],"iteration":86,"passed_time":0.04901508041,"remaining_time":0.007324092476},
{"learn":[4.692429407],"iteration":87,"passed_time":0.04959422184,"remaining_time":0.006762848432},
{"learn":[4.675027364],"iteration":88,"passed_time":0.05015506943,"remaining_time":0.006198941166},
{"learn":[4.662368584],"iteration":89,"passed_time":0.05069401543,"remaining_time":0.005632668381},
{"learn":[4.646206172],"iteration":90,"passed_time":0.05120382366,"remaining_time":0.005064114428},
{"learn":[4.641245848],"iteration":91,"passed_time":0.0517355667,"remaining_time":0.004498744931},
{"learn":[4.633900435],"iteration":92,"passed_time":0.05224317508,"remaining_time":0.003932281995},
{"learn":[4.624738236],"iteration":93,"passed_time":0.05279374261,"remaining_time":0.003369813358},
{"learn":[4.612798287],"iteration":94,"passed_time":0.05328876062,"remaining_time":0.002804671611},
{"learn":[4.605222001],"iteration":95,"passed_time":0.053792772,"remaining_time":0.0022413655},
{"learn":[4.601725912],"iteration":96,"passed_time":0.05430459332,"remaining_time":0.001679523505},
{"learn":[4.59722371],"iteration":97,"passed_time":0.05481261652,"remaining_time":0.001118624827},
{"learn":[4.580235665],"iteration":98,"passed_time":0.05533638082,"remaining_time":0.0005589533416},
{"learn":[4.57591791],"iteration":99,"passed_time":0.05583642528,"remaining_time":0}
]}